wusa/__init__.py
wusa/docker.py
wusa/exceptions.py
wusa/gh.py
wusa/main.py
wusa/output.py
wusa/runners.py
wusa-0.0.4.dist-info/entry_points.txt
wusa-0.0.4.dist-info/LICENSE
wusa-0.0.4.dist-info/WHEEL
wusa-0.0.4.dist-info/METADATA
wusa-0.0.4.dist-info/RECORD
