Metadata-Version: 2.1
Name: wusa
Version: 0.0.4
Summary: CLI for managing containerized self-hosted GitHub Actions Runner
License: MIT
Author: Anton Helm
Author-email: anton.helm@tecnico.ulisboa.pt
Requires-Python: >=3.7,<4.0
Classifier: License :: OSI Approved :: MIT License
Classifier: Programming Language :: Python :: 3
Classifier: Programming Language :: Python :: 3.7
Classifier: Programming Language :: Python :: 3.8
Classifier: Programming Language :: Python :: 3.9
Requires-Dist: aiohttp (>=3.7.3,<4.0.0)
Requires-Dist: docker (>=4.4.0,<5.0.0)
Requires-Dist: gidgethub (>=5.0.0,<6.0.0)
Requires-Dist: requests (>=2.25.1,<3.0.0)
Requires-Dist: rich (>=9.11.1,<10.0.0)
Requires-Dist: shortuuid (>=1.0.1,<2.0.0)
Requires-Dist: typer[all] (>=0.3.2,<0.4.0)
